pyspectools/.gitignore
pyspectools/__init__.py
pyspectools/_version.py
pyspectools/astro/__init__.py
pyspectools/astro/analysis.py
pyspectools/astro/conversions.py
pyspectools/astro/radiative.py
pyspectools/autofit.py
pyspectools/database.py
pyspectools/doubleresonance.py
pyspectools/figurefactory.py
pyspectools/fitting.py
pyspectools/ftmw_analysis.py
pyspectools/lineshapes.py
pyspectools/mmw/__init__.py
pyspectools/mmw/fft_routines.py
pyspectools/mmw/interpolation.py
pyspectools/mmw/mmw_analysis.py
pyspectools/mmw/plotting_func.py
pyspectools/models/VarMolDetect.pt
pyspectools/models/__init__.py
pyspectools/models/classes.py
pyspectools/models/torch_models.py
pyspectools/mpl_stylesheets/bokeh.yml
pyspectools/mpl_stylesheets/cfa.mplstyle
pyspectools/mpl_stylesheets/dark_presentation.mplstyle
pyspectools/mpl_stylesheets/presentation.mplstyle
pyspectools/mpl_stylesheets/publication.mplstyle
pyspectools/parameters.json
pyspectools/parsers.py
pyspectools/pickett_terms.yml
pyspectools/pypickett.py
pyspectools/qchem/__init__.py
pyspectools/qchem/analysis.py
pyspectools/qchem/extrapolation.py
pyspectools/qchem/heat_analysis.py
pyspectools/qchem/multiwell.py
pyspectools/qchem/parsers.py
pyspectools/qchem/utils.py
pyspectools/routines.py
pyspectools/spectra/__init__.py
pyspectools/spectra/analysis.py
pyspectools/spectra/assignment.py
pyspectools/spectra/report_template.html
pyspectools/templates/asymmetrictop.json
pyspectools/templates/asymmetrictop.yml
pyspectools/templates/diatomic_hf.json
pyspectools/templates/diatomic_hf.yml
pyspectools/templates/metaldicarbide.json
pyspectools/templates/metaldicarbide.yml
pyspectools/templates/oblatetop.json
pyspectools/templates/oblatetop.yml
pyspectools/templates/prolatetop.json
pyspectools/templates/prolatetop.yml
pyspectools/units.py
pyspectools-4.6.1.dist-info/LICENSE.txt
pyspectools-4.6.1.dist-info/WHEEL
pyspectools-4.6.1.dist-info/METADATA
pyspectools-4.6.1.dist-info/RECORD
